pyrestack/__init__.py
pyrestack/models.py
pyrestack/restack_client.py
pyrestack-0.1.4.dist-info/METADATA
pyrestack-0.1.4.dist-info/WHEEL
pyrestack-0.1.4.dist-info/top_level.txt
pyrestack-0.1.4.dist-info/zip-safe
pyrestack-0.1.4.dist-info/RECORD
