Metadata-Version: 2.1
Name: pyrestack
Version: 0.1.4
Summary: Python wrapper for ReStack API
Home-page: https://github.com/restack-project/restack
Author: Floris Heyvaert
Author-email: floris.heyvaert@gmail.com
License: MIT License
Keywords: pyrestack,setuptools
Classifier: Programming Language :: Python :: 3
Classifier: License :: OSI Approved :: MIT License
Classifier: Operating System :: OS Independent
Requires-Python: >=3.12.0
Requires-Dist: aiohttp <4.0,>=3.8.2
Requires-Dist: prometheus-client >=0.14.1
Requires-Dist: aiodns >=3.0.0
Provides-Extra: dev
Requires-Dist: black ==22.3.0 ; extra == 'dev'
Requires-Dist: isort ==5.10.1 ; extra == 'dev'
